Water/Engine.py
Water/__init__.py
Water_GM-0.1.3.dist-info/LICENSE
Water_GM-0.1.3.dist-info/METADATA
Water_GM-0.1.3.dist-info/WHEEL
Water_GM-0.1.3.dist-info/top_level.txt
Water_GM-0.1.3.dist-info/RECORD
