Metadata-Version: 2.1
Name: Water-GM
Version: 0.1.3
Summary: A modular terminal game engine to help developers build games in their terminal.
Author-email: TVRework <boxeigit@gmail.com>
Project-URL: Homepage, https://github.com/stack-community/water
Project-URL: Bug Tracker, https://github.com/stack-community/water/issues
Project-URL: Documentation, https://stack-community.github.io/Water/
Classifier: Programming Language :: Python :: 3
Classifier: License :: OSI Approved :: MIT License
Classifier: Operating System :: OS Independent
Requires-Python: >=3.7
License-File: LICENSE
